xtb_broker/__init__.py
xtb_broker/client.py
xtb_broker/utils.py
xtb_broker/xtb.py
xtb_broker/component/__init__.py
xtb_broker/component/constants.py
xtb_broker/component/exception.py
xtb_broker/component/frozen.py
xtb_broker/component/logger.py
xtb_broker/config/__init__.py
xtb_broker/config/constants.py
xtb_broker/config/exception.py
xtb_broker/config/frozen.py
xtb_broker/config/logger.py
xtb_broker/models/__init__.py
xtb_broker/models/arbitrage.py
xtb_broker/models/position.py
xtb_broker/models/shift.py
xtb_broker/models/symbol.py
xtb_broker/models/tick.py
xtb_broker/models/timetable.py
xtb_broker/models/trade.py
xtb_broker/models/transaction.py
xtb_broker-0.0.17.dist-info/LICENSE.txt
xtb_broker-0.0.17.dist-info/METADATA
xtb_broker-0.0.17.dist-info/WHEEL
xtb_broker-0.0.17.dist-info/top_level.txt
xtb_broker-0.0.17.dist-info/RECORD
