Metadata-Version: 2.1
Name: xtb-broker
Version: 0.0.17
Summary: XTB broker models, methods and tools
Home-page: https://pypi.org/project/xtb-broker/
Author: Arrubo
Author-email: UNKNOWN
License: UNKNOWN
Platform: UNKNOWN
